sharpai_hub/__init__.py
sharpai_hub/cli.py
sharpai_hub/sharpai_api.py
sharpai_hub/commands/__init__.py
sharpai_hub/commands/deepcamera.py
sharpai_hub/commands/deepcamera_local.py
sharpai_hub/commands/device.py
sharpai_hub/commands/falldetection.py
sharpai_hub/commands/screen_monitor.py
sharpai_hub/commands/user.py
sharpai_hub/commands/yoloparking.py
sharpai_hub/commands/yolov7_person_detector.py
sharpai_hub/commands/yolov7_reid.py
sharpai_hub/utils/__init__.py
sharpai_hub/utils/check_env.py
sharpai_hub/utils/config_tools.py
sharpai_hub/utils/debughelper.py
sharpai_hub/utils/get_id.py
sharpai_hub/utils/get_ip.py
sharpai_hub/utils/labelstudio.py
sharpai_hub/utils/screen_capture.py
sharpai_hub/utils/test_screen_capture.py
sharpai_hub-0.1.43.dist-info/LICENSE
sharpai_hub-0.1.43.dist-info/METADATA
sharpai_hub-0.1.43.dist-info/WHEEL
sharpai_hub-0.1.43.dist-info/entry_points.txt
sharpai_hub-0.1.43.dist-info/top_level.txt
sharpai_hub-0.1.43.dist-info/RECORD
