Metadata-Version: 2.1
Name: sharpai-hub
Version: 0.1.43
Summary: Client library to download application from sharpai hub
Home-page: https://github.com/SharpAI/sharpai_hub
Author: SharpAI LLC
Author-email: simba@sharpai.org
License: MIT
Keywords: model-hub machine-learning models natural-language-processing deep-learning Edge AI
Classifier: Intended Audience :: Developers
Classifier: Intended Audience :: Education
Classifier: Intended Audience :: Science/Research
Classifier: License :: OSI Approved :: MIT License
Classifier: Operating System :: OS Independent
Classifier: Programming Language :: Python :: 3
Classifier: Topic :: Scientific/Engineering :: Artificial Intelligence
Requires-Python: >=3.6.0
License-File: LICENSE
Requires-Dist: requests
Requires-Dist: tqdm
Requires-Dist: getmac >=0.8.3
Requires-Dist: pyyaml >=5.1
Requires-Dist: packaging >=20.9
Requires-Dist: Pillow ==8.4
Requires-Dist: importlib-metadata ; python_version < "3.8"
